README.md
setup.py
SmxUtils/ICitySMX.so
SmxUtils/__init__.py
SmxUtils/sm2.h
SmxUtils/sm2.py
SmxUtils/sm3.h
SmxUtils/sm3.py
SmxUtils.egg-info/PKG-INFO
SmxUtils.egg-info/SOURCES.txt
SmxUtils.egg-info/dependency_links.txt
SmxUtils.egg-info/top_level.txt