Metadata-Version: 1.1
Name: SmxUtils
Version: 1.0.0
Summary: SM Secret Utils
Home-page: https://github.com/yanzongzhen/SmxUtils
Author: yanzongzhen
Author-email: yanzongzhen127@outlook.com
License: MIT
Platform: UNKNOWN
Classifier: Intended Audience :: Developers
Classifier: License :: OSI Approved :: MIT License
Classifier: Natural Language :: English
Classifier: Programming Language :: Python :: 3.4
Classifier: Programming Language :: Python :: 3.5
Classifier: Programming Language :: Python :: 3.6
